{"basics":{"name":"Fakrul Islam Tushar","label":"PhD Candidate in Medical Imaging AI","email":"tushar.ece@duke.edu","phone":"+1 984-244-4464","url":"https://fitushar.github.io/","summary":"PhD Candidate at Duke University focusing on AI and In-Silico trials for lung cancer screening and diagnosis.","location":{"address":"Durham","postalCode":"NC","countryCode":"US","region":"North Carolina"},"profiles":[{"network":"GitHub","username":"fitushar","url":"https://github.com/fitushar"},{"network":"LinkedIn","username":"fitushar","url":"https://www.linkedin.com/in/fitushar/"}]},"work":[{"name":"Duke Radiology","position":"Research Fellow","startDate":"2019-10-01","endDate":"2021-02-01","summary":"Conducted research in AI and radiology, focusing on lung health imaging.","highlights":[]},{"name":"Duke Radiology","position":"Summer Intern","startDate":"2018-07-01","endDate":"2018-09-01","summary":"Assisted in radiology research projects.","highlights":[]}],"education":[{"institution":"Duke University","location":"Durham, NC, USA","area":"Electrical and Computer Engineering","studyType":"PhD","startDate":"2021-08-01","endDate":"2025-05-01","summary":"Research focuses on AI and In-Silico trials in lung health.","courses":[]},{"institution":"Erasmus+ MaIA","location":"France, Italy, Spain, USA","area":"Medical Imaging and Applications","studyType":"MSc","startDate":"2017-09-01","endDate":"2019-07-01","summary":"An interdisciplinary program focusing on advanced medical imaging techniques.","courses":[]},{"institution":"American International University-Bangladesh (AIUB)","location":"Dhaka, Bangladesh","area":"Electrical and Electronic Engineering","studyType":"BSc","startDate":"2013-01-01","endDate":"2017-02-01","summary":"Graduated with Cum Laude distinction.","courses":[]}],"awards":[{"title":"Best Poster","date":"2024-01-01","awarder":"Virtual Imaging Trials in Medicine","summary":"Awarded for exceptional research presentation on Virtual Imaging Trials."},{"title":"Travel Award","date":"2024-01-01","awarder":"SPIE Medical Imaging Conference","summary":"Recognized for outstanding research contributions."},{"title":"Cum Laude","date":"2017-01-01","awarder":"AIUB 17th Convocation","summary":"Graduated with distinction for exceptional academic performance."}],"projects":[{"name":"Virtual Lungs Screening Trials (VLST)","summary":"An in-silico alternative to clinical trials using digital human twin models, virtual scanners, and AI readers.","highlights":["Published at RSNA24, SPIE24 (Travel Award)","Best Poster at VITM24"],"startDate":"2023-01-01","url":"https://fitushar.github.io/VLST.github.io/"},{"name":"Transparency in Health AI","summary":"Exploring the transparency and limitations of AI in medical applications.","highlights":["Published in IEEE Access and SPIE22"],"startDate":"2022-01-01","url":"https://fitushar.github.io/ReviCOVID.github.io/"}],"languages":[{"language":"English","fluency":"Fluent"},{"language":"Bengali","fluency":"Native speaker"}]}